{
    "data": {
        "biome_coordinate": {
            "0": [0, 0],
            "24": [0, 1],
            "49": [0, 7],
            "14": [19, 0],
            "16": [53, 1],
            "7": [51, 3],
            "1": [57, 1],
            "4": [2, 62],
            "163": [0, 108],
            "45": [85, 19],
            "35": [81, 0],
            "27": [31, 52],
            "46": [32, 24],
            "21": [92, 31],
            "155": [76, 12],
            "23": [84, 14],
            "175": [58, 122],
            "25": [85, 124],
            "36": [110, 108],
            "48": [123, 18]
        },
        "total_biomes": 20
    }
}